dwr/__init__.py
dwr-0.1.0.dist-info/entry_points.txt
dwr-0.1.0.dist-info/LICENSE
dwr-0.1.0.dist-info/WHEEL
dwr-0.1.0.dist-info/METADATA
dwr-0.1.0.dist-info/RECORD
